gridimage.py
setup.py
GridImage.egg-info/PKG-INFO
GridImage.egg-info/SOURCES.txt
GridImage.egg-info/dependency_links.txt
GridImage.egg-info/entry_points.txt
GridImage.egg-info/not-zip-safe
GridImage.egg-info/top_level.txt