Metadata-Version: 1.0
Name: GridImage
Version: 0.2
Summary: A simple command-line tool for generating an image for background tiling to confirm a CSS grid.
Home-page: UNKNOWN
Author: Carl Meyer
Author-email: carl@dirtcircle.com
License: BSD
Platform: UNKNOWN
Classifier: Development Status :: 3 - Alpha
Classifier: Environment :: Console
Classifier: Intended Audience :: Developers
Classifier: License :: OSI Approved :: BSD License
Classifier: Natural Language :: English
Classifier: Operating System :: OS Independent
Classifier: Programming Language :: Python
